every_python/__init__.py
every_python/main.py
every_python/output.py
every_python/runner.py
every_python/utils.py
every_python-0.5.0.dist-info/METADATA
every_python-0.5.0.dist-info/WHEEL
every_python-0.5.0.dist-info/entry_points.txt
every_python-0.5.0.dist-info/licenses/LICENSE
every_python-0.5.0.dist-info/RECORD
