Metadata-Version: 2.4
Name: every-python
Version: 0.5.0
Summary: Build and run any commit of CPython
Project-URL: Homepage, https://github.com/savannahostrowski/every-python
Project-URL: Repository, https://github.com/savannahostrowski/every-python
Project-URL: Issues, https://github.com/savannahostrowski/gruyere/issues
Author-email: Savannah Ostrowski <savannah@python.org>
License: MIT
License-File: LICENSE
Keywords: bisect,build,cpython,python,testing
Classifier: Development Status :: 3 - Alpha
Classifier: Environment :: Console
Classifier: Intended Audience :: Developers
Classifier: License :: OSI Approved :: MIT License
Classifier: Operating System :: MacOS
Classifier: Operating System :: Microsoft :: Windows
Classifier: Operating System :: POSIX :: Linux
Classifier: Programming Language :: Python :: 3
Classifier: Programming Language :: Python :: 3.13
Classifier: Topic :: Utilities
Requires-Python: >=3.11
Requires-Dist: rich>=13.0.0
Requires-Dist: typer>=0.20.0
